unitycatalog_pydantic/__init__.py
unitycatalog_pydantic/map.py
unitycatalog_pydantic/model.py
unitycatalog_pydantic/operations.py
unitycatalog_pydantic/py.typed
unitycatalog_pydantic-0.1.0.dist-info/METADATA
unitycatalog_pydantic-0.1.0.dist-info/WHEEL
unitycatalog_pydantic-0.1.0.dist-info/entry_points.txt
unitycatalog_pydantic-0.1.0.dist-info/RECORD
