Metadata-Version: 2.4
Name: unitycatalog-pydantic
Version: 0.1.0
Summary: Manage Unity Catalog tables with Pydantic models
Author-email: Daniël Tom <detom89@gmail.com>
Requires-Python: >=3.9
Requires-Dist: pydantic>=2
Requires-Dist: unitycatalog-ai>=0.1
Requires-Dist: unitycatalog-client>=0.2
